ormir_xct/__init__.py
ormir_xct/autocontour/AutocontourKnee.py
ormir_xct/autocontour/README.md
ormir_xct/autocontour/__init__.py
ormir_xct/autocontour/autocontour.py
ormir_xct/autocontour/autocontour_gobj.py
ormir_xct/bone_mineral_density/README.md
ormir_xct/bone_mineral_density/__init__.py
ormir_xct/bone_mineral_density/bmd.py
ormir_xct/bone_mineral_density/bmd_masked.py
ormir_xct/joint_space_analysis/README.md
ormir_xct/joint_space_analysis/__init__.py
ormir_xct/joint_space_analysis/connected_check.py
ormir_xct/joint_space_analysis/jsw_main.py
ormir_xct/joint_space_analysis/jsw_morphometry.py
ormir_xct/segmentation/README.md
ormir_xct/segmentation/__init__.py
ormir_xct/segmentation/ipl_seg.py
ormir_xct/util/README.md
ormir_xct/util/__init__.py
ormir_xct/util/batch_file_converter.py
ormir_xct/util/file_converter.py
ormir_xct/util/file_reader.py
ormir_xct/util/generate_shapes.py
ormir_xct/util/hildebrand_thickness.py
ormir_xct/util/image_to_dicom.py
ormir_xct/util/process_ipl_log.py
ormir_xct/util/process_py_log.py
ormir_xct/util/scanco_rescale.py
ormir_xct/util/scrub_vms_extension.py
ormir_xct/util/seg_eval.py
ormir_xct/util/segmentation_evaluation.py
ormir_xct/util/sitk_itk.py
ormir_xct/util/sitk_vtk.py
ormir_xct-1.0.3.dist-info/licenses/LICENSE
ormir_xct-1.0.3.dist-info/METADATA
ormir_xct-1.0.3.dist-info/WHEEL
ormir_xct-1.0.3.dist-info/pbr.json
ormir_xct-1.0.3.dist-info/top_level.txt
ormir_xct-1.0.3.dist-info/RECORD
